[
    {
        "_id": "000000000000000000000000",
        "name": "The Marquee",
        "address": {
            "streetName": "4th Street",
            "streetNum": "1225",
            "city": "Sioux City",
            "state": "IA",
            "zipcode": "51101"
        },
        "description": "The Marquee is one of the upper Midwest's premier live music venue.  Specializing in top notch entertainment, craft beer, and genuine hospitality, The Marquee is your destination for local, regional, & national acts of all genres.",
        "picUrl": "https://static.wixstatic.com/media/c60f51_856926a5986746f09aad46cfb3135d6b~mv2_d_3125_1908_s_2.png/v1/fill/w_982,h_599,al_c,usm_0.66_1.00_0.01/c60f51_856926a5986746f09aad46cfb3135d6b~mv2_d_3125_1908_s_2.png",
        "websiteUrl": "https://www.themarqueelive.com/"
    },
    {
        "_id": "000000000000000000000001",
        "name": "Marty's Tap",
        "address": {
            "streetName": "Court Street",
            "streetNum": "1306",
            "city": "Sioux City",
            "state": "IA",
            "zipcode": "51105"
        },
        "description": "Some bigger but, NONE BETTER!!",
        "picUrl": "http://s3.amazonaws.com/product-images.imshopping.com/nimblebuy/1000-martys-tap-gift-certificates-for-500-3712712-regular.jpg",
        "websiteUrl": "http://www.martystap.com/"
    }
]